<PAMDataset>
  <Metadata>
    <MDI key="DataType">Generic</MDI>
  </Metadata>
  <PAMRasterBand band="1">
    <Description>Band_1</Description>
    <Histograms>
      <HistItem>
        <HistMin>0.1040000021457672</HistMin>
        <HistMax>0.9620000123977661</HistMax>
        <BucketCount>256</BucketCount>
        <IncludeOutOfRange>1</IncludeOutOfRange>
        <Approximate>0</Approximate>
        <HistCounts>23|39|53|60|68|98|81|69|78|37|43|47|33|46|45|39|70|60|58|97|76|80|63|42|78|66|78|101|74|96|142|114|129|96|109|158|143|129|185|142|155|153|115|159|132|154|245|207|249|288|180|219|357|274|390|288|277|372|218|215|288|234|197|281|213|305|201|177|263|207|206|298|170|141|211|195|223|161|201|208|198|218|327|206|240|355|289|473|330|364|505|367|352|368|273|353|247|237|439|274|283|356|309|351|434|327|394|346|413|433|281|332|462|286|398|593|426|578|477|495|699|503|505|774|596|635|926|793|998|847|887|1215|967|1044|1432|1118|1025|1391|994|1436|1008|1039|1413|1122|1118|1593|1293|1378|1880|1323|1707|1275|1395|1982|1461|1443|2075|1596|1525|2067|1502|2145|1651|1654|2120|1508|1619|2101|1581|1483|1642|934|1022|591|484|506|274|212|223|92|115|75|65|64|43|43|52|28|49|55|26|29|23|36|47|29|20|12|20|17|25|23|30|20|13|20|13|57|130|42|15|37|14|41|60|54|63|44|21|26|16|26|8|11|11|5|12|6|7|6|10|9|1|5|2|1|0|1|3|2|2|2|6|2|9|4|5|1|3|6|3|3|5|3|2|1</HistCounts>
      </HistItem>
    </Histograms>
    <Metadata>
      <MDI key="BandName">Band_1</MDI>
      <MDI key="RepresentationType">ATHEMATIC</MDI>
      <MDI key="STATISTICS_COVARIANCES">0.0170892334911285</MDI>
      <MDI key="STATISTICS_EXCLUDEDVALUES"></MDI>
      <MDI key="STATISTICS_MAXIMUM">0.96200001239777</MDI>
      <MDI key="STATISTICS_MEAN">0.55002106156429</MDI>
      <MDI key="STATISTICS_MINIMUM">0.10400000214577</MDI>
      <MDI key="STATISTICS_SKIPFACTORX">1</MDI>
      <MDI key="STATISTICS_SKIPFACTORY">1</MDI>
      <MDI key="STATISTICS_STDDEV">0.13072579504875</MDI>
    </Metadata>
  </PAMRasterBand>
</PAMDataset>
