<PAMDataset>
  <Metadata>
    <MDI key="DataType">Generic</MDI>
  </Metadata>
  <PAMRasterBand band="1">
    <Description>Band_1</Description>
    <Histograms>
      <HistItem>
        <HistMin>0.05200000107288361</HistMin>
        <HistMax>0.9829999804496765</HistMax>
        <BucketCount>256</BucketCount>
        <IncludeOutOfRange>1</IncludeOutOfRange>
        <Approximate>0</Approximate>
        <HistCounts>15|29|91|101|118|107|115|116|87|158|207|217|303|313|286|348|415|362|449|409|245|300|215|301|163|129|156|179|148|174|202|190|320|347|259|301|273|198|266|264|246|337|213|314|400|303|413|365|235|296|289|170|246|240|166|204|241|156|176|162|114|173|165|134|162|87|186|168|95|121|127|107|135|152|101|140|127|109|175|162|133|167|202|158|198|133|193|228|175|265|342|275|362|328|250|369|378|289|402|409|291|422|482|390|511|557|383|399|336|438|419|351|475|469|314|450|434|342|435|419|313|377|385|331|436|433|357|484|383|539|533|449|618|701|522|666|674|467|652|732|517|709|765|542|755|738|545|686|529|706|670|554|743|742|514|557|613|428|639|560|427|630|612|573|739|774|606|784|769|619|834|667|951|1058|710|1011|1099|755|952|1002|752|924|960|607|799|763|664|766|792|568|727|502|698|783|618|738|734|577|754|820|611|695|649|457|548|525|391|479|485|369|523|586|461|431|288|368|298|190|201|190|143|195|139|100|130|130|109|139|134|103|140|167|113|75|62|68|66|67|59|31|30|40|92|64|79|97|67|92|75|39|30|29|12|12|2|1</HistCounts>
      </HistItem>
    </Histograms>
    <Metadata>
      <MDI key="BandName">Band_1</MDI>
      <MDI key="RepresentationType">ATHEMATIC</MDI>
      <MDI key="STATISTICS_COVARIANCES">0.04528166552644334</MDI>
      <MDI key="STATISTICS_EXCLUDEDVALUES"></MDI>
      <MDI key="STATISTICS_MAXIMUM">0.98299998044968</MDI>
      <MDI key="STATISTICS_MEAN">0.55923472580713</MDI>
      <MDI key="STATISTICS_MINIMUM">0.052000001072884</MDI>
      <MDI key="STATISTICS_SKIPFACTORX">1</MDI>
      <MDI key="STATISTICS_SKIPFACTORY">1</MDI>
      <MDI key="STATISTICS_STDDEV">0.21279489074328</MDI>
    </Metadata>
  </PAMRasterBand>
</PAMDataset>
