<PAMDataset>
  <PAMRasterBand band="1">
    <Histograms>
      <HistItem>
        <HistMin>0.02800000086426735</HistMin>
        <HistMax>0.9240000247955322</HistMax>
        <BucketCount>256</BucketCount>
        <IncludeOutOfRange>1</IncludeOutOfRange>
        <Approximate>0</Approximate>
        <HistCounts>6|25|40|58|42|77|57|79|69|103|80|162|154|213|194|266|186|281|246|332|264|397|351|472|318|468|368|547|443|601|399|476|347|555|430|656|687|527|661|487|652|462|653|538|771|559|846|642|882|849|982|787|1122|906|1316|1047|1519|1203|1768|1420|1859|1329|1685|1231|1771|1651|2195|1581|2064|1600|2172|1633|1985|1986|1417|2012|1749|2378|1785|2505|1846|2338|1712|2235|1497|2138|1712|2467|1993|2972|2198|2978|2295|3275|2493|3228|2447|3368|2407|3559|2501|3312|2856|3645|2572|3533|2642|3340|2501|3351|3455|2515|3459|2680|3216|2089|2623|1872|2301|1591|1601|915|1441|1013|1276|687|715|475|531|277|378|362|459|298|320|213|193|155|211|144|174|125|118|64|72|83|56|45|34|78|24|36|32|55|45|36|17|22|31|57|15|12|12|32|24|36|8|15|16|22|21|37|16|4|7|33|13|14|8|10|5|9|17|16|19|6|6|7|13|16|17|14|15|2|9|2|7|4|6|2|4|7|3|0|3|1|0|1|2|1|0|0|0|1|1|4|1|0|0|6|0|2|2|1|1|1|1|1|2|1|1|1|0|0|3|1|2|2|3|2|2|0|1|0|1|0|1|1|1|2|0|1|1|0|0|1</HistCounts>
      </HistItem>
    </Histograms>
    <Metadata>
      <MDI key="RepresentationType">ATHEMATIC</MDI>
      <MDI key="STATISTICS_COVARIANCES">0.009280761023794416</MDI>
      <MDI key="STATISTICS_EXCLUDEDVALUES"></MDI>
      <MDI key="STATISTICS_MAXIMUM">0.92400002479553</MDI>
      <MDI key="STATISTICS_MEAN">0.33453117193346</MDI>
      <MDI key="STATISTICS_MINIMUM">0.028000000864267</MDI>
      <MDI key="STATISTICS_SKIPFACTORX">1</MDI>
      <MDI key="STATISTICS_SKIPFACTORY">1</MDI>
      <MDI key="STATISTICS_STDDEV">0.096336706523497</MDI>
    </Metadata>
  </PAMRasterBand>
</PAMDataset>
