<PAMDataset>
  <Metadata>
    <MDI key="DataType">Generic</MDI>
  </Metadata>
  <PAMRasterBand band="1">
    <Description>Band_1</Description>
    <Histograms>
      <HistItem>
        <HistMin>0.01099999994039536</HistMin>
        <HistMax>0.953000009059906</HistMax>
        <BucketCount>256</BucketCount>
        <IncludeOutOfRange>1</IncludeOutOfRange>
        <Approximate>0</Approximate>
        <HistCounts>341|822|1400|1840|3737|4469|3669|5907|7100|5699|7235|5789|5521|3376|4377|4186|2675|3486|3327|1821|1950|1850|1417|1944|2105|1769|1172|1638|1652|1156|1524|1361|934|1362|1163|829|1149|1106|1030|689|884|861|591|791|895|604|810|834|862|669|836|725|478|600|534|402|554|594|399|577|530|538|369|499|515|366|506|516|391|462|433|346|429|551|455|340|446|451|298|393|411|285|400|387|248|391|409|377|230|305|329|241|293|273|191|233|242|242|199|294|491|388|507|477|269|260|174|112|85|110|70|53|50|81|51|65|36|29|34|40|27|34|25|21|25|14|34|10|19|15|11|19|15|11|8|18|17|3|19|4|7|22|12|11|7|9|17|6|7|2|3|3|10|10|8|9|3|3|7|12|6|10|5|4|7|13|4|4|7|3|10|8|4|1|9|3|6|5|5|4|11|14|7|3|7|7|2|5|3|0|5|8|2|6|6|1|2|3|0|0|1|5|1|2|1|2|1|2|1|0|0|3|1|7|5|4|9|10|3|3|1|5|1|2|1|2|1|8|3|8|4|5|0|6|3|1|6|4|2|3|2|2|1|6|7|0|1|0|0|0|0|0|2|0|0|1</HistCounts>
      </HistItem>
    </Histograms>
    <Metadata>
      <MDI key="BandName">Band_1</MDI>
      <MDI key="RepresentationType">ATHEMATIC</MDI>
      <MDI key="STATISTICS_COVARIANCES">0.01058763101202186</MDI>
      <MDI key="STATISTICS_EXCLUDEDVALUES"></MDI>
      <MDI key="STATISTICS_MAXIMUM">0.95300000905991</MDI>
      <MDI key="STATISTICS_MEAN">0.11671025681909</MDI>
      <MDI key="STATISTICS_MINIMUM">0.010999999940395</MDI>
      <MDI key="STATISTICS_SKIPFACTORX">1</MDI>
      <MDI key="STATISTICS_SKIPFACTORY">1</MDI>
      <MDI key="STATISTICS_STDDEV">0.10289621476042</MDI>
    </Metadata>
  </PAMRasterBand>
</PAMDataset>
