<PAMDataset>
  <PAMRasterBand band="1">
    <Histograms>
      <HistItem>
        <HistMin>0</HistMin>
        <HistMax>0.6769999861717224</HistMax>
        <BucketCount>256</BucketCount>
        <IncludeOutOfRange>1</IncludeOutOfRange>
        <Approximate>0</Approximate>
        <HistCounts>213654|1733|986|1954|24|18|47|39|22|63|33|18|27|28|20|35|40|30|22|15|21|31|28|29|40|19|13|26|25|15|30|23|467|23|17|23|15|25|103|95|45|65|62|78|81|74|37|65|40|28|37|27|29|24|33|41|35|8|23|28|12|28|42|25|16|26|19|32|16|23|30|30|22|22|14|10|27|24|24|26|19|7|18|21|14|15|18|35|7|12|14|11|6|19|34|13|3|18|5|15|18|16|25|8|17|13|12|11|16|19|19|23|12|3|23|11|19|19|18|10|7|12|17|10|13|21|12|7|12|10|4|13|17|15|11|8|7|6|16|9|10|11|10|7|7|5|14|4|15|19|1|6|5|7|9|13|9|9|3|2|11|6|3|8|6|5|8|2|0|1|5|9|6|1|3|3|0|6|2|0|5|1|1|0|1|1|2|1|1|0|1|1|3|2|0|1|2|0|3|2|0|0|0|1|0|1|0|0|1|0|0|0|0|2|1|0|0|1|1|1|0|1|3|0|2|0|3|0|1|0|1|0|0|0|0|0|1|0|0|1|0|0|0|0|36|0|0|0|0|0|0|0|0|0|0|1</HistCounts>
      </HistItem>
    </Histograms>
    <Metadata>
      <MDI key="RepresentationType">ATHEMATIC</MDI>
      <MDI key="STATISTICS_COVARIANCES">0.0008079595760288182</MDI>
      <MDI key="STATISTICS_EXCLUDEDVALUES"></MDI>
      <MDI key="STATISTICS_MAXIMUM">0.67699998617172</MDI>
      <MDI key="STATISTICS_MEAN">0.0040284237164323</MDI>
      <MDI key="STATISTICS_MINIMUM">0</MDI>
      <MDI key="STATISTICS_SKIPFACTORX">1</MDI>
      <MDI key="STATISTICS_SKIPFACTORY">1</MDI>
      <MDI key="STATISTICS_STDDEV">0.028424629743038</MDI>
    </Metadata>
  </PAMRasterBand>
</PAMDataset>
