<PAMDataset>
  <PAMRasterBand band="1">
    <Histograms>
      <HistItem>
        <HistMin>0.3499999940395355</HistMin>
        <HistMax>0.9869999885559082</HistMax>
        <BucketCount>256</BucketCount>
        <IncludeOutOfRange>1</IncludeOutOfRange>
        <Approximate>0</Approximate>
        <HistCounts>1|0|0|0|0|0|0|1|0|1|0|0|0|0|0|2|0|0|0|0|0|1|0|0|0|1|0|0|0|0|0|0|1|0|1|0|0|0|0|0|0|0|0|0|0|1|0|1|4|2|0|0|0|2|5|3|0|1|0|2|1|0|3|2|2|1|2|3|4|7|4|4|8|6|5|10|7|10|19|13|33|23|57|45|62|44|82|70|107|74|135|94|110|91|153|110|204|145|231|156|309|213|331|229|393|272|423|324|601|447|685|504|828|610|1017|760|1279|942|1589|1059|1554|957|1377|926|1460|983|1475|961|1445|963|1468|959|1249|822|1145|765|1061|778|1147|655|1002|745|1019|578|842|526|776|490|661|423|611|341|451|259|339|196|307|185|273|153|242|156|214|145|220|149|224|131|162|103|150|83|130|70|112|66|117|61|96|53|80|61|66|45|80|42|74|31|49|41|59|42|40|22|51|36|55|28|51|30|56|21|51|26|42|28|37|21|34|22|46|20|41|24|37|22|37|33|41|31|49|27|53|36|41|39|59|35|52|40|63|34|52|47|60|45|80|43|72|46|100|44|97|50|79|45|65|33|52|34|46|23|22|9|2|2</HistCounts>
      </HistItem>
    </Histograms>
    <Metadata>
      <MDI key="RepresentationType">ATHEMATIC</MDI>
      <MDI key="STATISTICS_COVARIANCES">0.004850788586007582</MDI>
      <MDI key="STATISTICS_EXCLUDEDVALUES"></MDI>
      <MDI key="STATISTICS_MAXIMUM">0.98699998855591</MDI>
      <MDI key="STATISTICS_MEAN">0.68648404058591</MDI>
      <MDI key="STATISTICS_MINIMUM">0.34999999403954</MDI>
      <MDI key="STATISTICS_SKIPFACTORX">1</MDI>
      <MDI key="STATISTICS_SKIPFACTORY">1</MDI>
      <MDI key="STATISTICS_STDDEV">0.069647602873377</MDI>
    </Metadata>
  </PAMRasterBand>
</PAMDataset>
