<PAMDataset>
  <Metadata>
    <MDI key="DataType">Generic</MDI>
  </Metadata>
  <PAMRasterBand band="1">
    <Description>Band_1</Description>
    <Histograms>
      <HistItem>
        <HistMin>0.001000000047497451</HistMin>
        <HistMax>0.01999999955296516</HistMax>
        <BucketCount>256</BucketCount>
        <IncludeOutOfRange>1</IncludeOutOfRange>
        <Approximate>0</Approximate>
        <HistCounts>623|0|0|0|0|0|0|0|0|0|0|0|0|1270|0|0|0|0|0|0|0|0|0|0|0|0|641|0|0|0|0|0|0|0|0|0|0|0|0|0|391|0|0|0|0|0|0|0|0|0|0|0|0|230|0|0|0|0|0|0|0|0|0|0|0|0|0|158|0|0|0|0|0|0|0|0|0|0|0|0|133|0|0|0|0|0|0|0|0|0|0|0|0|118|0|0|0|0|0|0|0|0|0|0|0|0|0|98|0|0|0|0|0|0|0|0|0|0|0|0|86|0|0|0|0|0|0|0|0|0|0|0|0|0|77|0|0|0|0|0|0|0|0|0|0|0|0|63|0|0|0|0|0|0|0|0|0|0|0|0|0|39|0|0|0|0|0|0|0|0|0|0|0|0|28|0|0|0|0|0|0|0|0|0|0|0|0|32|0|0|0|0|0|0|0|0|0|0|0|0|0|26|0|0|0|0|0|0|0|0|0|0|0|0|27|0|0|0|0|0|0|0|0|0|0|0|0|0|71|0|0|0|0|0|0|0|0|0|0|0|0|92|0|0|0|0|0|0|0|0|0|0|0|0|0|127</HistCounts>
      </HistItem>
    </Histograms>
    <Metadata>
      <MDI key="BandName">Band_1</MDI>
      <MDI key="RepresentationType">ATHEMATIC</MDI>
      <MDI key="STATISTICS_COVARIANCES">2.524407417444923e-05</MDI>
      <MDI key="STATISTICS_EXCLUDEDVALUES"></MDI>
      <MDI key="STATISTICS_MAXIMUM">0.019999999552965</MDI>
      <MDI key="STATISTICS_MEAN">0.0050318706999253</MDI>
      <MDI key="STATISTICS_MINIMUM">0.0010000000474975</MDI>
      <MDI key="STATISTICS_SKIPFACTORX">1</MDI>
      <MDI key="STATISTICS_SKIPFACTORY">1</MDI>
      <MDI key="STATISTICS_STDDEV">0.0050243481342806</MDI>
    </Metadata>
  </PAMRasterBand>
</PAMDataset>
