<PAMDataset>
  <PAMRasterBand band="1">
    <Histograms>
      <HistItem>
        <HistMin>0.001000000047497451</HistMin>
        <HistMax>0.9520000219345093</HistMax>
        <BucketCount>256</BucketCount>
        <IncludeOutOfRange>1</IncludeOutOfRange>
        <Approximate>0</Approximate>
        <HistCounts>60028|16365|8075|2372|2804|1380|1190|2555|840|477|359|287|356|300|228|291|288|344|278|350|361|256|183|376|383|193|262|251|232|236|237|223|256|173|249|354|302|355|253|269|195|268|242|223|155|209|201|183|141|179|175|135|204|182|192|131|173|165|164|105|134|117|92|97|103|101|71|99|83|79|62|75|95|56|80|74|84|52|84|73|75|64|78|78|60|75|75|70|53|69|79|79|65|86|75|56|48|49|89|50|15|5|7|11|9|13|5|3|2|4|6|7|7|6|0|10|6|2|13|3|1|1|10|5|2|2|2|4|2|0|0|3|3|2|0|0|1|2|5|5|2|2|7|10|0|3|8|7|4|2|0|0|0|1|0|0|0|0|0|0|0|0|0|0|1|0|0|0|0|0|1|1|2|1|4|0|0|0|0|0|0|0|0|4|0|2|1|1|1|1|0|0|0|0|0|0|0|0|0|0|0|0|0|0|0|0|0|0|0|0|0|1|0|1|0|0|0|0|0|0|0|0|0|0|0|0|1|2|0|0|0|0|1|0|0|0|0|1|0|0|0|0|0|0|1|0|0|0|0|0|0|0|0|0|0|2</HistCounts>
      </HistItem>
    </Histograms>
    <Metadata>
      <MDI key="RepresentationType">ATHEMATIC</MDI>
      <MDI key="STATISTICS_COVARIANCES">0.004181856628978755</MDI>
      <MDI key="STATISTICS_EXCLUDEDVALUES"></MDI>
      <MDI key="STATISTICS_MAXIMUM">0.95200002193451</MDI>
      <MDI key="STATISTICS_MEAN">0.027246321911668</MDI>
      <MDI key="STATISTICS_MINIMUM">0.0010000000474975</MDI>
      <MDI key="STATISTICS_SKIPFACTORX">1</MDI>
      <MDI key="STATISTICS_SKIPFACTORY">1</MDI>
      <MDI key="STATISTICS_STDDEV">0.064667276338027</MDI>
    </Metadata>
  </PAMRasterBand>
</PAMDataset>
