<PAMDataset>
  <PAMRasterBand band="1">
    <Histograms>
      <HistItem>
        <HistMin>0</HistMin>
        <HistMax>0.9779999852180481</HistMax>
        <BucketCount>256</BucketCount>
        <IncludeOutOfRange>1</IncludeOutOfRange>
        <Approximate>0</Approximate>
        <HistCounts>60694|59584|39954|28746|25787|17096|7692|8757|7227|6091|5460|3852|2349|2792|2339|2214|2147|2006|1452|2113|2016|1824|2065|1598|1058|1335|1320|1232|1184|1111|840|1141|1166|1175|1225|1199|927|1259|1220|1149|1146|1161|836|1112|1035|1053|973|988|806|1148|1062|1054|1023|1023|783|1105|1023|911|912|871|707|869|867|790|758|722|567|747|827|737|689|691|562|709|704|690|719|682|515|661|708|660|653|615|496|588|623|576|543|540|559|395|441|492|474|482|400|316|395|412|387|434|432|322|421|408|391|415|348|262|394|397|357|407|395|301|356|336|350|329|364|262|356|364|333|324|299|232|320|351|313|312|292|251|342|313|299|306|246|189|248|297|235|263|252|196|219|202|215|200|169|115|161|129|162|148|130|118|128|121|104|112|117|90|134|110|96|96|79|162|1302|771|583|303|161|175|101|93|95|99|102|135|155|315|298|279|190|194|119|173|142|138|145|146|86|109|126|115|108|79|79|79|90|115|100|104|51|89|77|49|57|77|73|70|75|58|49|69|41|68|43|57|63|57|48|63|59|49|55|50|57|48|44|56|51|61|36|49|41|40|43|38|15|20|27|21|23|21|8|3|4|4|4|0|0|1</HistCounts>
      </HistItem>
    </Histograms>
    <Metadata>
      <MDI key="RepresentationType">ATHEMATIC</MDI>
      <MDI key="STATISTICS_COVARIANCES">0.02601559144324579</MDI>
      <MDI key="STATISTICS_EXCLUDEDVALUES"></MDI>
      <MDI key="STATISTICS_MAXIMUM">0.97799998521805</MDI>
      <MDI key="STATISTICS_MEAN">0.088844499481027</MDI>
      <MDI key="STATISTICS_MINIMUM">0</MDI>
      <MDI key="STATISTICS_SKIPFACTORX">1</MDI>
      <MDI key="STATISTICS_SKIPFACTORY">1</MDI>
      <MDI key="STATISTICS_STDDEV">0.16129349473319</MDI>
    </Metadata>
  </PAMRasterBand>
</PAMDataset>
